iipimage/storage.py
iipimage/__init__.py
iipimage/fields.py
django_iipimage-1.0.dist-info/METADATA
django_iipimage-1.0.dist-info/metadata.json
django_iipimage-1.0.dist-info/DESCRIPTION.rst
django_iipimage-1.0.dist-info/WHEEL
django_iipimage-1.0.dist-info/RECORD
django_iipimage-1.0.dist-info/top_level.txt
