Metadata-Version: 2.0
Name: django-iipimage
Version: 1.0
Summary: Django app to provide integration with IIPImage server
Home-page: https://github.com/kcl-ddh/django-iipimage
Author: Jamie Norrish
Author-email: jamie@artefact.org.nz
License: UNKNOWN
Platform: UNKNOWN
Classifier: Framework :: Django
Classifier: Intended Audience :: Developers
Classifier: Programming Language :: Python
Classifier: Programming Language :: Python :: 2
Classifier: Programming Language :: Python :: 3
